{"user1": {"username": "user1", "password": "pass1", "created": "2020-12-26 23:43:36"}, "user2": {"username": "user2", "password": "pass2", "created": "2020-12-26 23:43:43"}, "user3": {"username": "user3", "password": "pass3", "created": "2020-12-27 00:51:22"}, "pesho": {"username": "pesho", "password": "1234", "created": "2020-12-27 01:11:13"}, "goshko": {"username": "goshko", "password": "a1b2", "created": "2020-12-27 01:12:14"}, "mara": {"username": "mara", "password": "aaaa", "created": "2020-12-27 01:12:38"}, "": {"username": "", "password": "", "created": "2020-12-27 13:56:39"}, "Dorcho": {"username": "Dorcho", "password": "dorcho1", "created": "2020-12-29 02:03:56"}}